{"type":"Topology","arcs":[[[0,250],[40,54],[67,-53],[-41,-54],[-66,53]],[[106,172],[34,52],[65,-50],[-39,-50],[-60,48]],[[204,107],[30,55],[60,-37],[-29,-57],[-61,39]],[[334,100],[74,-45],[-31,-55],[-72,44],[29,56]]],"transform":{"scale":[0.000002143835770484612,0.0000020515167046790335],"translate":[105.28520777484908,-4.710734023790096]},"objects":{"map":{"type":"GeometryCollection","geometries":[{"arcs":[[0]],"type":"Polygon","properties":{"ID":"18/01"}},{"arcs":[[1]],"type":"Polygon","properties":{"ID":"18/02"}},{"arcs":[[2]],"type":"Polygon","properties":{"ID":"17/01"}},{"arcs":[[3]],"type":"Polygon","properties":{"ID":"17/02"}}]}}}